LICENSE
README.md
pyproject.toml
setup.cfg
setup.py
weasel/__init__.py
weasel/classification/__init__.py
weasel/classification/dictionary_based/__init__.py
weasel/classification/dictionary_based/_boss.py
weasel/classification/dictionary_based/_muse.py
weasel/classification/dictionary_based/_muse_v2.py
weasel/classification/dictionary_based/_weasel.py
weasel/classification/dictionary_based/_weasel_v2.py
weasel/transformations/__init__.py
weasel/transformations/collection/__init__.py
weasel/transformations/collection/dictionary_based/__init__.py
weasel/transformations/collection/dictionary_based/_sfa_dilation.py
weasel_classifier.egg-info/PKG-INFO
weasel_classifier.egg-info/SOURCES.txt
weasel_classifier.egg-info/dependency_links.txt
weasel_classifier.egg-info/not-zip-safe
weasel_classifier.egg-info/requires.txt
weasel_classifier.egg-info/top_level.txt