Metadata-Version: 2.4
Name: weasel-classifier
Version: 0.3.0
Summary: A Random Dilated Dictionary Transform for Fast, Accurate and Constrained Memory Time Series Classification
Home-page: https://github.com/patrickzib/dictionary
Author: patrickzib
Author-email: patrickzib <void@void.com>
License:                     GNU GENERAL PUBLIC LICENSE
Project-URL: repository, https://github.com/patrickzib/dictionary
Keywords: machine-learning,time-series,dictionary,classification
Classifier: Intended Audience :: Science/Research
Classifier: Intended Audience :: Developers
Classifier: License :: OSI Approved :: BSD License
Classifier: Programming Language :: Python
Classifier: Topic :: Software Development
Classifier: Topic :: Scientific/Engineering
Classifier: Operating System :: Microsoft :: Windows
Classifier: Operating System :: POSIX
Classifier: Operating System :: Unix
Classifier: Operating System :: MacOS
Classifier: Programming Language :: Python :: 3
Classifier: Programming Language :: Python :: 3.9
Classifier: Programming Language :: Python :: 3.10
Classifier: Programming Language :: Python :: 3.11
Classifier: Programming Language :: Python :: 3.12
Classifier: Programming Language :: Python :: 3.13
Requires-Python: >=3.9,<3.14
License-File: LICENSE
Requires-Dist: joblib>=1.1.1
Requires-Dist: aeon>=1.0.0
Requires-Dist: numba<0.62.0,>=0.55
Requires-Dist: numpy<2.3.0,>=1.21.0
Requires-Dist: pandas<2.3.0,>=2.0.0
Requires-Dist: scikit-learn<1.7.0,>=1.0.0
Requires-Dist: scipy<1.16.0,>=1.9.0
Dynamic: author
Dynamic: home-page
Dynamic: license-file
Dynamic: requires-python
